flask_rpc/__init__.py
flask_rpc/exceptions.py
flask_rpc/latest.py
flask_rpc/validation.py
flask_rpc/version_1_0/__init__.py
flask_rpc/version_1_0/_protocols.py
flask_rpc/version_1_0/auth_session_key.py
flask_rpc/version_1_0/model.py
flask_rpc/version_1_0/request.py
flask_rpc/version_1_0/response.py
flask_rpc/version_1_0/rpc.py
flask_rpc/version_1_0/utilities.py
flask_rpc/version_1_1/__init__.py
flask_rpc/version_1_1/_protocols.py
flask_rpc/version_1_1/auth_session_key.py
flask_rpc/version_1_1/model.py
flask_rpc/version_1_1/request.py
flask_rpc/version_1_1/response.py
flask_rpc/version_1_1/rpc.py
flask_rpc/version_1_1/utilities.py
flask_rpc-1.6.2.dist-info/LICENSE.txt
flask_rpc-1.6.2.dist-info/WHEEL
flask_rpc-1.6.2.dist-info/METADATA
flask_rpc-1.6.2.dist-info/RECORD
