Metadata-Version: 2.3
Name: flask-rpc
Version: 1.6.2
Summary: Turn Flask into a simple RPC server
Author-email: David Carmichael <david@uilix.com>
Classifier: License :: OSI Approved :: MIT License
Classifier: Framework :: Flask
Classifier: Natural Language :: English
Requires-Dist: Flask
Requires-Dist: pydantic
